Metadata-Version: 2.1
Name: tsassure-feature-Extractor
Version: 0.1
Summary: UNKNOWN
License: UNKNOWN
Platform: UNKNOWN
Requires-Dist: numpy
Requires-Dist: pandas
Requires-Dist: openpyxl
